malloy_mcp_server/__about__.py
malloy_mcp_server/__init__.py
malloy_mcp_server/errors.py
malloy_mcp_server/py.typed
malloy_mcp_server/server.py
malloy_mcp_server-0.1.1.dist-info/METADATA
malloy_mcp_server-0.1.1.dist-info/WHEEL
malloy_mcp_server-0.1.1.dist-info/entry_points.txt
malloy_mcp_server-0.1.1.dist-info/licenses/LICENSE
malloy_mcp_server-0.1.1.dist-info/RECORD
