Metadata-Version: 2.4
Name: malloy-mcp-server
Version: 0.1.1
Summary: MCP server for Malloy queries
Project-URL: Documentation, https://github.com/namabile/malloy-mcp-server#readme
Project-URL: Issues, https://github.com/namabile/malloy-mcp-server/issues
Project-URL: Source, https://github.com/namabile/malloy-mcp-server
Author-email: Nick Amabile <nick.amabile@gmail.com>
License-Expression: MIT
License-File: LICENSE
Keywords: malloy,mcp,query,server
Classifier: Development Status :: 4 - Beta
Classifier: Programming Language :: Python
Classifier: Programming Language :: Python :: 3.11
Classifier: Programming Language :: Python :: Implementation :: CPython
Classifier: Programming Language :: Python :: Implementation :: PyPy
Requires-Python: >=3.11
Requires-Dist: malloy-publisher-client>=0.1.1
Requires-Dist: mcp>=1.6.0
